{
  "publicPath": "/blog/_nuxt/",
  "all": [
    "../server/index.spa.html",
    "../server/index.ssr.html",
    "3fa76f6238e741175c2f.js",
    "5bca33a1be5186011024.js",
    "7a823a57b4c618e3818d.js",
    "LICENSES",
    "a3811e802580f2e83b99.js",
    "a7a5212c1a490fb88343.js",
    "b1dfacb483bb5245ce83.js",
    "b4632e37e734aba6580b.js",
    "dc70d99437a4c4223f7a.js",
    "e67e39fb1ead1e3f355d.js"
  ],
  "initial": [
    "5bca33a1be5186011024.js",
    "dc70d99437a4c4223f7a.js",
    "a7a5212c1a490fb88343.js",
    "7a823a57b4c618e3818d.js"
  ],
  "async": [
    "3fa76f6238e741175c2f.js",
    "a3811e802580f2e83b99.js",
    "b1dfacb483bb5245ce83.js",
    "b4632e37e734aba6580b.js",
    "e67e39fb1ead1e3f355d.js"
  ],
  "modules": {
    "14976974": [
      9
    ],
    "22333287": [
      11
    ],
    "29163214": [
      10
    ],
    "32047259": [
      11
    ],
    "42425736": [
      10
    ],
    "51766966": [
      4
    ],
    "53412800": [
      10
    ],
    "56722750": [
      10
    ],
    "84517462": [
      11
    ],
    "8aadda2c": [
      4
    ],
    "36644b92": [
      10
    ],
    "5c7115d0": [
      10
    ],
    "3b614858": [
      10
    ],
    "c43cf0d2": [
      7
    ],
    "f1200b78": [
      10
    ],
    "3745f3ba": [
      10
    ],
    "71ce579a": [
      10
    ],
    "6c14d506": [
      10
    ],
    "0a68d5d6": [
      10
    ],
    "7928a062": [
      10
    ],
    "234f51e9": [
      10
    ],
    "341aa2f7": [
      10
    ],
    "4c07f658": [
      10
    ],
    "4984c1d5": [
      10
    ],
    "403bfaa8": [
      10
    ],
    "1b3c20da": [
      7
    ],
    "90bc4e86": [
      10
    ],
    "19518f01": [
      10
    ],
    "4686d3ae": [
      10
    ],
    "442259df": [
      10
    ],
    "2931ca69": [
      10
    ],
    "56e5f8f7": [
      7
    ],
    "d46609ae": [
      4
    ],
    "5e10674a": [
      4
    ],
    "7421a2f0": [
      4
    ],
    "b970a534": [
      4
    ],
    "39782f42": [
      4
    ],
    "11cde09a": [
      4
    ],
    "ac047d92": [
      4
    ],
    "719e7389": [
      4
    ],
    "e79426e4": [
      4
    ],
    "6668e91a": [
      4
    ],
    "34d09ca8": [
      4
    ],
    "5c9b05b5": [
      4
    ],
    "35e66d9f": [
      4
    ],
    "4eb578cc": [
      4
    ],
    "aa2b2ec2": [
      4
    ],
    "db0f0be8": [
      4
    ],
    "4f8c772a": [
      4
    ],
    "d020466a": [
      4
    ],
    "82c566c6": [
      4
    ],
    "fbf62c68": [
      10
    ],
    "5e25d2ee": [
      10
    ],
    "f2df02d6": [
      10
    ],
    "a04e0446": [
      10
    ],
    "4e9dd81f": [
      10
    ],
    "5067d89e": [
      10
    ],
    "09f305a9": [
      10
    ],
    "5f6aa3d5": [
      10
    ],
    "435766c4": [
      10
    ],
    "517c2d4f": [
      10
    ],
    "6cc259d1": [
      7
    ],
    "642fd22a": [
      10
    ],
    "78a836fc": [
      10
    ],
    "2bc02d24": [
      10
    ],
    "638a7972": [
      10
    ],
    "9fb0bbe0": [
      10
    ],
    "778ed9b2": [
      10
    ],
    "084a35b4": [
      10
    ],
    "0c763a2c": [
      10
    ],
    "0d9295c1": [
      10
    ],
    "30bd0ba2": [
      10
    ],
    "2254f3cc": [
      10
    ],
    "5c8cc7de": [
      10
    ],
    "6a63de4a": [
      10
    ],
    "cf23e6f8": [
      7
    ],
    "1a67356c": [
      7
    ],
    "6a6104ed": [
      7
    ],
    "75201f50": [
      7
    ],
    "6ceae3d2": [
      10
    ],
    "1f8547da": [
      10
    ],
    "37901f32": [
      10
    ],
    "cdc1240c": [
      10
    ],
    "78ed9784": [
      10
    ],
    "ee2688ce": [
      10
    ],
    "78f2233a": [
      10
    ],
    "8ba572bc": [
      10
    ],
    "f1bc0806": [
      10
    ],
    "eb2c2c30": [
      10
    ],
    "92f9320c": [
      10
    ],
    "9dc01ca0": [
      10
    ],
    "30e425f8": [
      10
    ],
    "72fa51e4": [
      10
    ],
    "4adeb41a": [
      10
    ],
    "4f611ab0": [
      10
    ],
    "3fcab4f3": [
      10
    ],
    "1a5fea9d": [
      4
    ],
    "730da6a9": [
      4
    ],
    "c9b497ca": [
      4
    ],
    "74dff1d0": [
      10
    ],
    "1d7732a4": [
      7
    ],
    "6da8812d": [
      4
    ],
    "742ef39e": [
      10
    ],
    "b4e9bde0": [
      10
    ],
    "7e7f8a22": [
      10
    ],
    "3e91ba00": [
      10
    ],
    "4e1119fe": [
      10
    ],
    "78fb3aa6": [
      10
    ],
    "7b781ea2": [
      10
    ],
    "51afd30b": [
      10
    ],
    "1bf157ce": [
      10
    ],
    "22ff567b": [
      10
    ],
    "0355b7e4": [
      10
    ],
    "4249a4f7": [
      10
    ],
    "bab28c14": [
      10
    ],
    "14012bbf": [
      10
    ],
    "8465e2cc": [
      10
    ],
    "eb544b44": [
      10
    ],
    "039a0441": [
      10
    ],
    "f6aa6258": [
      10
    ],
    "6a50fab4": [
      10
    ],
    "a26036ac": [
      10
    ],
    "3151b3de": [
      10
    ],
    "2b0bd8f0": [
      10
    ],
    "e3fe313c": [
      10
    ],
    "61f45f26": [
      10
    ],
    "54f35661": [
      4
    ],
    "4aacb8e3": [
      7
    ],
    "345f7566": [
      10
    ],
    "09583663": [
      10
    ],
    "1b0177c8": [
      10
    ],
    "54e8f187": [
      10
    ],
    "0f17d280": [
      10
    ],
    "e84b5be6": [
      10
    ],
    "4873bcef": [
      10
    ],
    "74325faf": [
      10
    ],
    "534ad790": [
      10
    ],
    "5ccc12cc": [
      10
    ],
    "2d8d4746": [
      10
    ],
    "47e7d28e": [
      10
    ],
    "6936c578": [
      10
    ],
    "5eaa16da": [
      10
    ],
    "6b6f590e": [
      10
    ],
    "7a8294b4": [
      10
    ],
    "01e5f4f8": [
      10
    ],
    "0f3b5cc3": [
      10
    ],
    "4e66844f": [
      10
    ],
    "9102429c": [
      10
    ],
    "0d8828a0": [
      10
    ],
    "060837c6": [
      10
    ],
    "c06e25b4": [
      10
    ],
    "7ad993c2": [
      10
    ],
    "eb1c973a": [
      10
    ],
    "739b4558": [
      10
    ],
    "28b79438": [
      10
    ],
    "5c1b119a": [
      10
    ],
    "8ee0e886": [
      10
    ],
    "26cdc68e": [
      10
    ],
    "a2b04e7a": [
      10
    ],
    "2168ef89": [
      10
    ],
    "0ea1e5d2": [
      10
    ],
    "4092b9ea": [
      10
    ],
    "4090740f": [
      10
    ],
    "14db2c1b": [
      7
    ],
    "478677ad": [
      7
    ],
    "1fc68455": [
      10
    ],
    "3f42a072": [
      7
    ],
    "964b87fa": [
      7
    ],
    "3692d91a": [
      7
    ],
    "0a73943d": [
      10
    ],
    "c9626c62": [
      4
    ],
    "3af2b8f0": [
      4
    ],
    "7426f3a9": [
      10
    ],
    "764952b4": [
      10
    ],
    "74db95de": [
      10
    ],
    "24c91049": [
      10
    ],
    "79f84e3f": [
      10
    ],
    "4c102e32": [
      10
    ],
    "3429f657": [
      10
    ],
    "5288f6a1": [
      10
    ],
    "72e0790f": [
      10
    ],
    "e2085c9c": [
      10
    ],
    "322217b4": [
      10
    ],
    "30bb2d96": [
      10
    ],
    "e4c0ecfa": [
      10
    ],
    "a810ec7e": [
      10
    ],
    "df6c197c": [
      10
    ],
    "6a9a49c8": [
      10
    ],
    "7b678e78": [
      10
    ],
    "480e48a8": [
      10
    ],
    "079ee444": [
      10
    ],
    "639eeedf": [
      10
    ],
    "433422a4": [
      10
    ],
    "13e2aa96": [
      10
    ],
    "0f99c4f4": [
      10
    ],
    "219f8a15": [
      10
    ],
    "32189b9f": [
      10
    ],
    "25d50dbe": [
      10
    ],
    "8684ed8c": [
      10
    ],
    "378e8f2a": [
      10
    ],
    "b4fa4ec8": [
      10
    ],
    "7a282851": [
      10
    ],
    "965b2ce6": [
      10
    ],
    "0fec6fe4": [
      10
    ],
    "b2562940": [
      10
    ],
    "26b0c9d8": [
      10
    ],
    "44ed24a0": [
      10
    ],
    "57fb1962": [
      10
    ],
    "07fcf35d": [
      10
    ],
    "9026b00c": [
      10
    ],
    "117413ba": [
      10
    ],
    "d419f8a2": [
      10
    ],
    "3be1f8cd": [
      10
    ],
    "6f64e967": [
      10
    ],
    "653c13ee": [
      10
    ],
    "3eda5ab7": [
      4
    ],
    "5cac0768": [
      4
    ],
    "62ac7843": [
      4
    ],
    "52c5bcb4": [
      4
    ],
    "2d2ee5b4": [
      7
    ],
    "7c4fa3ee": [
      7
    ],
    "8d9265a2": [
      7
    ],
    "a95eaeb8": [
      10
    ],
    "cc156574": [
      10
    ],
    "21b793bc": [
      10
    ],
    "365670e7": [
      10
    ],
    "5a5d2e43": [
      7
    ],
    "d663c724": [
      10
    ],
    "04598705": [
      10
    ],
    "2dc87874": [
      10
    ],
    "41e4dc52": [
      10
    ],
    "8a16aa9c": [
      10
    ],
    "584cc94a": [
      10
    ],
    "e515c1e8": [
      10
    ],
    "6164d8cb": [
      10
    ],
    "1e8aa4f5": [
      10
    ],
    "1d3a56a0": [
      10
    ],
    "7fdd39da": [
      10
    ],
    "02963bac": [
      10
    ],
    "482818fb": [
      10
    ],
    "ac3f4c3c": [
      10
    ],
    "43822e42": [
      10
    ],
    "94e24664": [
      7
    ],
    "5b478860": [
      10
    ],
    "a83322b4": [
      10
    ],
    "0c7e7206": [
      10
    ],
    "46f0f703": [
      10
    ],
    "306d9f16": [
      10
    ],
    "c1d16e8a": [
      10
    ],
    "408be859": [
      10
    ],
    "3fd21b6c": [
      10
    ],
    "3c314dcc": [
      10
    ],
    "f23c17c4": [
      7
    ],
    "1f4ccbb1": [
      7
    ],
    "f4711978": [
      7
    ],
    "46f86753": [
      7
    ],
    "56dd4a28": [
      7
    ],
    "7d5ab5e7": [
      7
    ],
    "430e5e79": [
      7
    ],
    "56f5f23c": [
      7
    ],
    "4c83fb35": [
      4
    ],
    "1b667d2e": [
      7
    ],
    "2ef1f51e": [
      7
    ],
    "53ce0cdf": [
      7
    ],
    "d8023e32": [
      9
    ],
    "3a358426": [
      9
    ],
    "c4654e66": [
      9
    ],
    "c45a657e": [
      9
    ],
    "1436220a": [
      9
    ],
    "14a669b3": [
      9
    ],
    "14a9984c": [
      9
    ],
    "14fe2552": [
      9
    ],
    "151225a6": [
      9
    ],
    "c4531f8e": [
      9
    ],
    "c44a0822": [
      9
    ],
    "c44836a6": [
      9
    ],
    "c442c232": [
      9
    ],
    "c441d974": [
      9
    ],
    "c440f0b6": [
      9
    ],
    "c43e367c": [
      9
    ],
    "c43d4dbe": [
      9
    ],
    "c4317c18": [
      9
    ],
    "c4211ebc": [
      9
    ],
    "c41e6482": [
      9
    ],
    "c41baa48": [
      9
    ],
    "c4154d16": [
      9
    ],
    "c411aa1e": [
      9
    ],
    "c808b4c6": [
      9
    ],
    "c7db3faa": [
      9
    ],
    "c4023580": [
      9
    ],
    "c3ef1dea": [
      9
    ],
    "41c9abf8": [
      9
    ],
    "401547b8": [
      9
    ],
    "3fef188c": [
      9
    ],
    "3f7d73c6": [
      9
    ],
    "3f425b88": [
      9
    ],
    "3f3bfe56": [
      9
    ],
    "3ea258e8": [
      9
    ],
    "c3ec63b0": [
      9
    ],
    "c3e8c0b8": [
      9
    ],
    "2ec7de9c": [
      9
    ],
    "2ce51c82": [
      9
    ],
    "c3e7d7fa": [
      9
    ],
    "c3e6ef3c": [
      9
    ],
    "c3dcef12": [
      9
    ],
    "c3d5a922": [
      9
    ],
    "c3d034ae": [
      9
    ],
    "c3cd7a74": [
      9
    ],
    "1b828d9d": [
      9
    ],
    "1b85bc36": [
      9
    ],
    "c3c71d42": [
      9
    ],
    "c3c0c010": [
      9
    ],
    "c3be05d6": [
      9
    ],
    "c3b6bfe6": [
      9
    ],
    "4a8d270a": [
      9
    ],
    "c3ae9138": [
      9
    ],
    "c3a0ee16": [
      9
    ],
    "c39d4b1e": [
      9
    ],
    "c3951c70": [
      9
    ],
    "c3926236": [
      9
    ],
    "5d79cb94": [
      9
    ],
    "c385a7d2": [
      9
    ],
    "c37804b0": [
      9
    ],
    "c3771bf2": [
      9
    ],
    "86148d56": [
      9
    ],
    "c36c330a": [
      9
    ],
    "c3591b74": [
      9
    ],
    "c3500408": [
      9
    ],
    "c346ec9c": [
      9
    ],
    "c3451b20": [
      9
    ],
    "c3443262": [
      9
    ],
    "c34349a4": [
      9
    ],
    "c33dd530": [
      9
    ],
    "c33a3238": [
      9
    ],
    "c332ec48": [
      9
    ],
    "c3271aa2": [
      9
    ],
    "c3228eec": [
      9
    ],
    "c320bd70": [
      9
    ],
    "c314030c": [
      9
    ],
    "c3106014": [
      9
    ],
    "c30e8e98": [
      9
    ],
    "c30da5da": [
      9
    ],
    "c30bd45e": [
      9
    ],
    "c3083166": [
      9
    ],
    "c30748a8": [
      9
    ],
    "2828d6e9": [
      9
    ],
    "c3065fea": [
      9
    ],
    "c301d434": [
      9
    ],
    "c2fa8e44": [
      9
    ],
    "c2f7d40a": [
      9
    ],
    "c2f176d8": [
      9
    ],
    "1d1a4b0a": [
      9
    ],
    "c2efa55c": [
      9
    ],
    "b142564a": [
      9
    ],
    "c2b918d4": [
      9
    ],
    "c2b1d2e4": [
      9
    ],
    "d7d730ba": [
      9
    ],
    "c27e0096": [
      9
    ],
    "c2788c22": [
      9
    ],
    "c26bd1be": [
      9
    ],
    "c26ae900": [
      9
    ],
    "c2674608": [
      9
    ],
    "c265748c": [
      9
    ],
    "c2648bce": [
      9
    ],
    "c2600018": [
      9
    ],
    "c25f175a": [
      9
    ],
    "4cfa4dc4": [
      9
    ],
    "c25e2e9c": [
      9
    ],
    "c25b7462": [
      9
    ],
    "c25a8ba4": [
      9
    ],
    "c2525cf6": [
      9
    ],
    "c24eb9fe": [
      9
    ],
    "3c5aad39": [
      9
    ],
    "c24ce882": [
      9
    ],
    "c24bffc4": [
      9
    ],
    "e5b00322": [
      9
    ],
    "3cb7dd4c": [
      9
    ],
    "c242e858": [
      9
    ],
    "3d7ef7d6": [
      9
    ],
    "3d7f6c35": [
      9
    ],
    "2d0346c6": [
      9
    ],
    "2854e894": [
      9
    ],
    "c22d1688": [
      9
    ],
    "c226b956": [
      9
    ],
    "c21f7366": [
      9
    ],
    "177a1185": [
      9
    ],
    "c212b902": [
      9
    ],
    "d3640582": [
      9
    ],
    "c1b8b788": [
      9
    ],
    "2821a752": [
      9
    ],
    "2866bfba": [
      9
    ],
    "29154e3a": [
      9
    ],
    "42c5fcec": [
      11
    ],
    "5d3b2319": [
      9
    ],
    "7f0fc0e4": [
      9
    ],
    "3fdbdf55": [
      9
    ],
    "6df3069c": [
      11
    ],
    "dfd7680c": [
      11
    ],
    "a7cf264c": [
      11
    ],
    "16ac0a1a": [
      11
    ],
    "1ec74a82": [
      11
    ],
    "7068b40b": [
      11
    ],
    "290230c4": [
      11
    ],
    "395beb96": [
      11
    ],
    "6ec609de": [
      11
    ],
    "8040d746": [
      11
    ],
    "b69a6a48": [
      11
    ],
    "2d1bcd9f": [
      11
    ],
    "f6afd10c": [
      11
    ],
    "92efc226": [
      11
    ],
    "50c57aab": [
      11
    ],
    "fe4f01f6": [
      11
    ],
    "c1a7bf60": [
      11
    ],
    "549bf66b": [
      11
    ],
    "77d16092": [
      11
    ],
    "5e8bfaae": [
      11
    ],
    "2a127b0d": [
      11
    ],
    "76b48d0e": [
      11
    ],
    "2822bbd8": [
      11
    ],
    "474be718": [
      11
    ],
    "2b463a48": [
      11
    ],
    "c0089556": [
      11
    ],
    "2c469b94": [
      11
    ],
    "3b62b5d6": [
      11
    ],
    "25f9e1d8": [
      11
    ],
    "71d03079": [
      11
    ],
    "3916bb3e": [
      11
    ],
    "9308eb18": [
      11
    ],
    "bf28461e": [
      11
    ],
    "30c1bb35": [
      11
    ],
    "2d0e2a7d": [
      11
    ],
    "2d0f133b": [
      11
    ],
    "ca181ca8": [
      11
    ],
    "a23f6c08": [
      11
    ],
    "2d461422": [
      11
    ],
    "2d47713f": [
      11
    ],
    "36c94c04": [
      11
    ],
    "4e30ad46": [
      11
    ],
    "dc32e166": [
      11
    ],
    "10fbc6a6": [
      11
    ],
    "c24445f2": [
      11
    ],
    "61efe69e": [
      11
    ],
    "2eb5d459": [
      11
    ],
    "5e574360": [
      11
    ],
    "2ec3ebda": [
      11
    ],
    "8b387b0a": [
      11
    ],
    "2f0a615f": [
      11
    ],
    "97d4d98c": [
      11
    ],
    "6f7a3012": [
      11
    ],
    "29229c66": [
      11
    ],
    "304bc3bc": [
      11
    ],
    "d080f1dc": [
      11
    ],
    "309b50ad": [
      11
    ],
    "52cbcda1": [
      11
    ],
    "5b2b201e": [
      11
    ],
    "8da9d56a": [
      11
    ],
    "31db55ed": [
      11
    ],
    "0dfb5297": [
      11
    ],
    "155830ae": [
      11
    ],
    "0998d7b0": [
      11
    ],
    "3052572c": [
      11
    ],
    "308461f2": [
      11
    ],
    "4673740e": [
      11
    ],
    "4005aaa0": [
      11
    ],
    "4369046e": [
      11
    ],
    "33c3181c": [
      11
    ],
    "a1d252f8": [
      11
    ],
    "482646e1": [
      11
    ],
    "8bdf9776": [
      11
    ],
    "9bfa79c4": [
      11
    ],
    "653563d4": [
      11
    ],
    "84f404f8": [
      11
    ],
    "5861322e": [
      11
    ],
    "65cd37c6": [
      11
    ],
    "35ce4f3d": [
      11
    ],
    "127a13e1": [
      11
    ],
    "f3f424b8": [
      11
    ],
    "a1ad0c8a": [
      11
    ],
    "7772ebf4": [
      11
    ],
    "373983be": [
      11
    ],
    "06cd1414": [
      11
    ],
    "8f905090": [
      11
    ],
    "6108a46c": [
      11
    ],
    "023e8a42": [
      11
    ],
    "5050cf10": [
      11
    ],
    "2453a578": [
      11
    ],
    "316d3f69": [
      11
    ],
    "0cf7e929": [
      11
    ],
    "63d5356a": [
      11
    ],
    "288fa6b0": [
      11
    ],
    "3db1c277": [
      11
    ],
    "3ef5df0e": [
      11
    ],
    "3ff96ef3": [
      11
    ],
    "46cb7452": [
      11
    ],
    "53bca610": [
      11
    ],
    "2acc9156": [
      11
    ],
    "4c12e795": [
      11
    ],
    "3c9fe03d": [
      11
    ],
    "3cb70f2a": [
      11
    ],
    "8a9c47fc": [
      11
    ],
    "477b1ede": [
      11
    ],
    "47d79e9f": [
      11
    ],
    "16faa773": [
      11
    ],
    "3d8f6fce": [
      11
    ],
    "7b771caf": [
      11
    ],
    "2911e9a6": [
      11
    ],
    "05c0d5f3": [
      11
    ],
    "138115dd": [
      11
    ],
    "0a06fabf": [
      11
    ],
    "915ead8e": [
      11
    ],
    "e8ca9640": [
      11
    ],
    "50ea878e": [
      11
    ],
    "30e5d4f0": [
      11
    ],
    "9845c952": [
      11
    ],
    "3f821ae5": [
      11
    ],
    "7dc659c6": [
      11
    ],
    "60b01ce2": [
      11
    ],
    "6e1b0476": [
      11
    ],
    "06f153cf": [
      11
    ],
    "175f3886": [
      11
    ],
    "3a380c2e": [
      11
    ],
    "a0dcda94": [
      11
    ],
    "6ef690ea": [
      11
    ],
    "42da11aa": [
      11
    ],
    "58cc488b": [
      11
    ],
    "245f16e2": [
      11
    ],
    "39750f41": [
      11
    ],
    "f3ac890e": [
      11
    ],
    "3a3d65d6": [
      11
    ],
    "8b1fad4e": [
      11
    ],
    "2bad757e": [
      11
    ],
    "55b76f38": [
      11
    ],
    "6fecd428": [
      11
    ],
    "888f08e0": [
      11
    ],
    "36bd7a5e": [
      11
    ],
    "44d38e52": [
      11
    ],
    "36bc91a0": [
      11
    ],
    "3ca4d2e9": [
      11
    ],
    "464b7d37": [
      11
    ],
    "4338687e": [
      11
    ],
    "8a9cf2c2": [
      11
    ],
    "46dcf3f7": [
      11
    ],
    "307ab0b3": [
      11
    ],
    "cea65e70": [
      11
    ],
    "4797541d": [
      11
    ],
    "0d8ca05c": [
      11
    ],
    "0b225627": [
      11
    ],
    "4b500698": [
      11
    ],
    "a2494708": [
      11
    ],
    "1ce42b32": [
      11
    ],
    "1e8e93de": [
      11
    ],
    "2b5f6a62": [
      11
    ],
    "483d3f90": [
      11
    ],
    "4872e35a": [
      11
    ],
    "48759d94": [
      11
    ],
    "6a445bc4": [
      11
    ],
    "dd716896": [
      11
    ],
    "61d1e001": [
      11
    ],
    "fe6d744c": [
      11
    ],
    "b1bdeb44": [
      11
    ],
    "3ce41c6f": [
      11
    ],
    "2c222d47": [
      11
    ],
    "2f0159b6": [
      11
    ],
    "494acf9f": [
      11
    ],
    "49652d25": [
      11
    ],
    "4986d09b": [
      11
    ],
    "837af4da": [
      11
    ],
    "a0630720": [
      11
    ],
    "055024ab": [
      11
    ],
    "5c7010c7": [
      11
    ],
    "49b989cc": [
      11
    ],
    "261eea51": [
      11
    ],
    "3870aad5": [
      11
    ],
    "471adb81": [
      11
    ],
    "3fe36784": [
      11
    ],
    "553fba32": [
      11
    ],
    "4d23dfc8": [
      11
    ],
    "9ff5ee10": [
      11
    ],
    "4ec9849c": [
      11
    ],
    "d63cb0c0": [
      11
    ],
    "703e315d": [
      11
    ],
    "460aa464": [
      11
    ],
    "e259aad6": [
      11
    ],
    "1cd0b92e": [
      2
    ],
    "abfefe92": [
      2
    ],
    "69db1f6d": [
      2
    ],
    "5da9920b": [
      2
    ],
    "7b5ec208": [
      2
    ],
    "2e600150": [
      8
    ],
    "01914aae": [
      8
    ],
    "35b27834": [
      8
    ],
    "472635fd": [
      8
    ],
    "68b062f5": [
      8
    ],
    "3f910198": [
      6
    ],
    "335714a8": [
      6
    ],
    "a6d04700": [
      6
    ],
    "67357ed4": [
      6
    ],
    "1a32c0de": [
      6
    ]
  },
  "assetsMapping": {
    "3fa76f6238e741175c2f.js": "6b2ac3fc",
    "5bca33a1be5186011024.js": "6fca0322",
    "7a823a57b4c618e3818d.js": "1a3ae26b",
    "a3811e802580f2e83b99.js": "2a130dde",
    "a7a5212c1a490fb88343.js": "7ea1d828",
    "b1dfacb483bb5245ce83.js": "69ae3ae3",
    "b4632e37e734aba6580b.js": "5a7f2bf5",
    "dc70d99437a4c4223f7a.js": "0859c165",
    "e67e39fb1ead1e3f355d.js": "41906d42"
  }
}