{
  "publicPath": "/blog/_nuxt/",
  "all": [
    "../server/index.spa.html",
    "../server/index.ssr.html",
    "14b5292713a87fca71f8.js",
    "33d9b6ed32073e596aa8.js",
    "3a46c8f4da3860394409.js",
    "3b9d5998a43562325cfb.js",
    "5119cc306d04eb726ae3.js",
    "56c0a54331558de3e2a5.js",
    "86adc34d2adfe7f90fd5.js",
    "8e63b0601df76b940aa3.js",
    "8f80bb4528de006b1026.js",
    "8fa100176adb079e28cc.js",
    "908a02b7f09d711d2316.js",
    "93f2a62fcd394e319f30.js",
    "LICENSES",
    "b02a6835c41741c65550.js",
    "e21fefb901f3e6c8bfa9.js",
    "f1dddc5ee7797b101467.js"
  ],
  "initial": [
    "3a46c8f4da3860394409.js",
    "8fa100176adb079e28cc.js",
    "56c0a54331558de3e2a5.js",
    "86adc34d2adfe7f90fd5.js"
  ],
  "async": [
    "14b5292713a87fca71f8.js",
    "33d9b6ed32073e596aa8.js",
    "3b9d5998a43562325cfb.js",
    "5119cc306d04eb726ae3.js",
    "8e63b0601df76b940aa3.js",
    "8f80bb4528de006b1026.js",
    "908a02b7f09d711d2316.js",
    "93f2a62fcd394e319f30.js",
    "b02a6835c41741c65550.js",
    "e21fefb901f3e6c8bfa9.js",
    "f1dddc5ee7797b101467.js"
  ],
  "modules": {
    "17074076": [
      7
    ],
    "21650598": [
      17
    ],
    "22257326": [
      15
    ],
    "27326782": [
      7
    ],
    "29143302": [
      11
    ],
    "38383057": [
      13
    ],
    "39231049": [
      7
    ],
    "44054853": [
      13
    ],
    "46125396": [
      7
    ],
    "61332302": [
      8
    ],
    "61486425": [
      12
    ],
    "61649327": [
      9
    ],
    "76057027": [
      13
    ],
    "76131349": [
      13
    ],
    "76295978": [
      13
    ],
    "76664332": [
      13
    ],
    "76728937": [
      13
    ],
    "76811517": [
      13
    ],
    "77268006": [
      10
    ],
    "86336752": [
      7
    ],
    "54f6c10a": [
      8
    ],
    "2cfc77ba": [
      11
    ],
    "7f8f4c1b": [
      11
    ],
    "2634fc1e": [
      11
    ],
    "e66a203e": [
      11
    ],
    "687795ca": [
      11
    ],
    "2219a780": [
      11
    ],
    "18320f94": [
      11
    ],
    "7e1a4380": [
      11
    ],
    "1c6e4450": [
      11
    ],
    "57527ab6": [
      11
    ],
    "3e173674": [
      11
    ],
    "e16e758c": [
      11
    ],
    "573affb5": [
      11
    ],
    "54b7cb32": [
      11
    ],
    "32b2ea5a": [
      7
    ],
    "6569afc0": [
      11
    ],
    "01fd5e9e": [
      11
    ],
    "9b6ed532": [
      7
    ],
    "5c40ee94": [
      7
    ],
    "301aa949": [
      8
    ],
    "0d787d2a": [
      8
    ],
    "5e8f1110": [
      8
    ],
    "1ea92bf0": [
      8
    ],
    "29f096ba": [
      8
    ],
    "7a24c425": [
      8
    ],
    "d729a152": [
      8
    ],
    "aeb7d37c": [
      8
    ],
    "e90434b4": [
      8
    ],
    "e13625b8": [
      8
    ],
    "27e41a32": [
      8
    ],
    "14ceb308": [
      8
    ],
    "822202d0": [
      8
    ],
    "25d356b2": [
      8
    ],
    "b58fc628": [
      8
    ],
    "1bdb5724": [
      8
    ],
    "4161fb24": [
      8
    ],
    "310332b2": [
      8
    ],
    "7104cb16": [
      8
    ],
    "16d64c8f": [
      11
    ],
    "2b9f49a1": [
      11
    ],
    "b3571f1e": [
      11
    ],
    "9942bad0": [
      11
    ],
    "5da0d4e0": [
      11
    ],
    "459b20e2": [
      11
    ],
    "6903132c": [
      11
    ],
    "f76d80a4": [
      7
    ],
    "30b452fa": [
      11
    ],
    "92d832f0": [
      11
    ],
    "7e525702": [
      11
    ],
    "1bf518b1": [
      11
    ],
    "7c029a4a": [
      11
    ],
    "5def7913": [
      11
    ],
    "6e8c2275": [
      11
    ],
    "1a4fa42e": [
      11
    ],
    "ba4dd382": [
      11
    ],
    "5e0379b6": [
      11
    ],
    "eb8aa6ae": [
      11
    ],
    "1f367b2e": [
      11
    ],
    "5f9f739e": [
      11
    ],
    "490f9632": [
      7
    ],
    "459875f0": [
      7
    ],
    "778109ef": [
      11
    ],
    "4e2da8a0": [
      11
    ],
    "10e5f4f5": [
      11
    ],
    "dfc69286": [
      11
    ],
    "1f514f7e": [
      11
    ],
    "71988b36": [
      11
    ],
    "1f55db34": [
      11
    ],
    "12d8ab5a": [
      11
    ],
    "5acef12a": [
      11
    ],
    "c1a192d2": [
      11
    ],
    "0c4e13f3": [
      11
    ],
    "6387c20a": [
      8
    ],
    "bea388f2": [
      8
    ],
    "07570579": [
      8
    ],
    "4674aaa6": [
      11
    ],
    "c6da5166": [
      8
    ],
    "0a4fe594": [
      11
    ],
    "174d68ce": [
      11
    ],
    "e3921ea6": [
      11
    ],
    "273d899d": [
      11
    ],
    "7fe64941": [
      11
    ],
    "1f5ef2a0": [
      11
    ],
    "640df2da": [
      11
    ],
    "af737ab6": [
      11
    ],
    "48ad1bce": [
      11
    ],
    "3a863c58": [
      11
    ],
    "4ce6d5de": [
      11
    ],
    "449d7c41": [
      8
    ],
    "5007ae80": [
      7
    ],
    "17a57490": [
      11
    ],
    "6dbdae42": [
      7
    ],
    "3aa3e7b4": [
      11
    ],
    "d1031d8c": [
      7
    ],
    "11fec08b": [
      11
    ],
    "fc91d4ec": [
      11
    ],
    "17e88b9d": [
      11
    ],
    "84a0fd60": [
      11
    ],
    "57ab2768": [
      11
    ],
    "873e059c": [
      11
    ],
    "41a96556": [
      11
    ],
    "67ff1c29": [
      11
    ],
    "d519ffba": [
      11
    ],
    "3093a22b": [
      11
    ],
    "13933ac7": [
      11
    ],
    "abfe6b54": [
      11
    ],
    "865788aa": [
      11
    ],
    "6831115e": [
      11
    ],
    "07ddbea1": [
      11
    ],
    "2081c746": [
      11
    ],
    "27bc5a12": [
      11
    ],
    "7a9c2fe2": [
      11
    ],
    "f35f1686": [
      11
    ],
    "0e424ea0": [
      11
    ],
    "66d1ddae": [
      11
    ],
    "166ff442": [
      11
    ],
    "34c052b4": [
      11
    ],
    "52b9810a": [
      7
    ],
    "16c3cd18": [
      11
    ],
    "000a5c35": [
      7
    ],
    "706d42d0": [
      7
    ],
    "0a01f854": [
      7
    ],
    "1bb9fec0": [
      11
    ],
    "1f56b1ea": [
      11
    ],
    "787debfe": [
      8
    ],
    "dc228d30": [
      8
    ],
    "74e85374": [
      11
    ],
    "1cad0aae": [
      11
    ],
    "5d87657b": [
      11
    ],
    "03c233e8": [
      11
    ],
    "62a41ddc": [
      11
    ],
    "5743378f": [
      11
    ],
    "2b273f1a": [
      11
    ],
    "102e097e": [
      11
    ],
    "f7b238dc": [
      11
    ],
    "bf7b8796": [
      11
    ],
    "2080a57a": [
      11
    ],
    "27b87659": [
      11
    ],
    "764b5920": [
      11
    ],
    "d6b94d44": [
      11
    ],
    "85cfd176": [
      11
    ],
    "556dfd8e": [
      11
    ],
    "8d6cfcf2": [
      11
    ],
    "79e377eb": [
      11
    ],
    "c71c753e": [
      11
    ],
    "6e3514fc": [
      11
    ],
    "5539911e": [
      11
    ],
    "5c114819": [
      11
    ],
    "0f74d6de": [
      11
    ],
    "e2d4331c": [
      11
    ],
    "5ee6bfa2": [
      11
    ],
    "3d5bf39b": [
      11
    ],
    "22da8f06": [
      11
    ],
    "359d9b08": [
      11
    ],
    "6327eb79": [
      11
    ],
    "e922da58": [
      11
    ],
    "c01cb460": [
      11
    ],
    "277355c1": [
      11
    ],
    "4eabcaba": [
      11
    ],
    "7041e7d2": [
      11
    ],
    "22604f9a": [
      11
    ],
    "a54f6ddc": [
      11
    ],
    "19c7a0c0": [
      11
    ],
    "d9b7ce06": [
      11
    ],
    "08715c7d": [
      11
    ],
    "a50c2ce8": [
      11
    ],
    "248dc86a": [
      11
    ],
    "2d09fc44": [
      11
    ],
    "be913796": [
      8
    ],
    "632e49cd": [
      8
    ],
    "7d25cb7e": [
      8
    ],
    "7c7e0c4e": [
      8
    ],
    "387192d1": [
      7
    ],
    "633b4582": [
      7
    ],
    "f1dcd686": [
      7
    ],
    "190ec937": [
      7
    ],
    "050a97e0": [
      7
    ],
    "0c0288f6": [
      7
    ],
    "2d9dffb0": [
      7
    ],
    "5ad76007": [
      7
    ],
    "247b27d9": [
      7
    ],
    "f366208a": [
      7
    ],
    "aa025ec0": [
      7
    ],
    "878c9e8e": [
      7
    ],
    "5ef0fce2": [
      7
    ],
    "5dfded3d": [
      7
    ],
    "63e1f66c": [
      7
    ],
    "facaac24": [
      7
    ],
    "5b853cbc": [
      7
    ],
    "7881f613": [
      7
    ],
    "3f5ab470": [
      7
    ],
    "e14f7322": [
      7
    ],
    "7612e08b": [
      7
    ],
    "5be7aa50": [
      7
    ],
    "47a6c154": [
      7
    ],
    "30f374f5": [
      7
    ],
    "24bf1212": [
      7
    ],
    "5d1b698b": [
      7
    ],
    "7b332658": [
      7
    ],
    "5e1bcad7": [
      7
    ],
    "169a26d9": [
      7
    ],
    "3d80c7b5": [
      7
    ],
    "f9d2ca08": [
      7
    ],
    "126c9101": [
      7
    ],
    "2f43d691": [
      7
    ],
    "9c9b7118": [
      7
    ],
    "acebf15c": [
      7
    ],
    "5ee359c0": [
      7
    ],
    "5ee4427e": [
      7
    ],
    "61c49f5c": [
      7
    ],
    "7449c76f": [
      7
    ],
    "1bd6a659": [
      7
    ],
    "5f1b4365": [
      7
    ],
    "5f1ca082": [
      7
    ],
    "11697e01": [
      7
    ],
    "2a4c8bfa": [
      7
    ],
    "ca916f2c": [
      7
    ],
    "2882ac83": [
      7
    ],
    "b0a2d3b8": [
      7
    ],
    "32e21ae4": [
      7
    ],
    "608b039c": [
      7
    ],
    "5c8b0dad": [
      7
    ],
    "60991b1d": [
      7
    ],
    "0bc8a518": [
      7
    ],
    "60df90a2": [
      7
    ],
    "5dd8bdd8": [
      7
    ],
    "02f597aa": [
      7
    ],
    "6220f2ff": [
      7
    ],
    "bedf7fa2": [
      7
    ],
    "62707ff0": [
      7
    ],
    "3deb09e4": [
      7
    ],
    "2c1d5464": [
      7
    ],
    "6b1d0064": [
      7
    ],
    "63b08530": [
      7
    ],
    "16cc0bb4": [
      7
    ],
    "22a3f31e": [
      7
    ],
    "12ba7a05": [
      7
    ],
    "0df78cec": [
      7
    ],
    "57b9de91": [
      7
    ],
    "195b8063": [
      7
    ],
    "4c39bd8b": [
      7
    ],
    "6598475f": [
      7
    ],
    "1c0d32e1": [
      7
    ],
    "50f6fffe": [
      7
    ],
    "5cd1cbbc": [
      7
    ],
    "6cecae0a": [
      7
    ],
    "6e061cf1": [
      7
    ],
    "493cace1": [
      7
    ],
    "31b707f1": [
      7
    ],
    "6e9df0e3": [
      7
    ],
    "67a37e80": [
      7
    ],
    "63def67e": [
      7
    ],
    "e252b27e": [
      7
    ],
    "1c1fd618": [
      7
    ],
    "50c8c1b7": [
      7
    ],
    "690eb301": [
      7
    ],
    "14205bd3": [
      7
    ],
    "7deede56": [
      7
    ],
    "4f673232": [
      7
    ],
    "ead12b88": [
      7
    ],
    "99e1ed0a": [
      7
    ],
    "12b2333e": [
      7
    ],
    "42b3a9ec": [
      7
    ],
    "cea2cef4": [
      7
    ],
    "34c769b0": [
      7
    ],
    "0602d1aa": [
      7
    ],
    "46827b94": [
      7
    ],
    "47c6982b": [
      7
    ],
    "48ca2810": [
      7
    ],
    "4f9c2d6f": [
      7
    ],
    "88bb4226": [
      7
    ],
    "765066b2": [
      7
    ],
    "54e3a0b2": [
      7
    ],
    "6e750f80": [
      7
    ],
    "6e8c3e6d": [
      7
    ],
    "0c16be9f": [
      7
    ],
    "329a5b21": [
      7
    ],
    "5f5e847c": [
      7
    ],
    "2e818d50": [
      7
    ],
    "6f649f11": [
      7
    ],
    "54ccf272": [
      7
    ],
    "0267bf69": [
      7
    ],
    "1c51cefa": [
      7
    ],
    "15b391fc": [
      7
    ],
    "6250e1d4": [
      7
    ],
    "1751643d": [
      7
    ],
    "59bb40ab": [
      7
    ],
    "0e58ffea": [
      7
    ],
    "6937fd98": [
      7
    ],
    "71574a28": [
      7
    ],
    "6c24e78c": [
      7
    ],
    "7f616ef9": [
      7
    ],
    "5856366c": [
      7
    ],
    "64b38d00": [
      7
    ],
    "138de1f1": [
      7
    ],
    "1c87ef13": [
      7
    ],
    "4c69bbe4": [
      7
    ],
    "74af40ed": [
      7
    ],
    "3403b98e": [
      7
    ],
    "2d2fcfff": [
      7
    ],
    "75a882c4": [
      7
    ],
    "11e06ad6": [
      7
    ],
    "0b5a481c": [
      7
    ],
    "0b2f9a1c": [
      7
    ],
    "4626d8b6": [
      7
    ],
    "3b8e27de": [
      7
    ],
    "6d3e5515": [
      7
    ],
    "b97df222": [
      7
    ],
    "59813d26": [
      7
    ],
    "116f66d4": [
      7
    ],
    "76a8bd95": [
      7
    ],
    "116fdb33": [
      7
    ],
    "e3ec94f4": [
      7
    ],
    "7820ac7a": [
      7
    ],
    "d6c569ca": [
      7
    ],
    "0c16693c": [
      7
    ],
    "78b2233a": [
      7
    ],
    "5e882f94": [
      7
    ],
    "bd04ec36": [
      7
    ],
    "796c8360": [
      7
    ],
    "1ed30adf": [
      7
    ],
    "22a93c04": [
      7
    ],
    "62d6ec75": [
      7
    ],
    "90a7d4ce": [
      7
    ],
    "2e2a95b5": [
      7
    ],
    "2fd4fe61": [
      7
    ],
    "74f0885c": [
      7
    ],
    "7a126ed3": [
      7
    ],
    "7a48129d": [
      7
    ],
    "7a4accd7": [
      7
    ],
    "58a2e98a": [
      7
    ],
    "bae49390": [
      7
    ],
    "7958c5de": [
      7
    ],
    "cf5fa892": [
      7
    ],
    "ff123fbe": [
      7
    ],
    "4e2a86f2": [
      7
    ],
    "b62b0d38": [
      7
    ],
    "1d5fe77c": [
      7
    ],
    "7b1ffee2": [
      7
    ],
    "7b3a5c68": [
      7
    ],
    "7b5bffde": [
      7
    ],
    "546d2920": [
      7
    ],
    "1cc4d8cd": [
      7
    ],
    "0e20ddc8": [
      7
    ],
    "2fb27fb8": [
      7
    ],
    "528a42e9": [
      7
    ],
    "376554d4": [
      7
    ],
    "ec54e51c": [
      7
    ],
    "3147d9f8": [
      7
    ],
    "19393d47": [
      7
    ],
    "5e10734f": [
      7
    ],
    "7ef90f0b": [
      7
    ],
    "39ba1864": [
      7
    ],
    "1cfb6555": [
      7
    ],
    "66506a79": [
      7
    ],
    "a72ee506": [
      7
    ],
    "2a74d1b3": [
      8
    ],
    "0eb5496a": [
      8
    ],
    "476b9744": [
      13
    ],
    "23cf716c": [
      13
    ],
    "75c72950": [
      13
    ],
    "75cc9dc4": [
      13
    ],
    "6c65dea7": [
      13
    ],
    "6cc72611": [
      13
    ],
    "6cd62650": [
      13
    ],
    "6cd954e9": [
      13
    ],
    "6d2de1ef": [
      13
    ],
    "6d41e243": [
      13
    ],
    "75d040bc": [
      13
    ],
    "75d4cc72": [
      13
    ],
    "75d5b530": [
      13
    ],
    "75d86f6a": [
      13
    ],
    "75d8e3c9": [
      13
    ],
    "75d95828": [
      13
    ],
    "75dab545": [
      13
    ],
    "75db29a4": [
      13
    ],
    "75e11277": [
      13
    ],
    "75e94125": [
      13
    ],
    "75ea9e42": [
      13
    ],
    "75ebfb5f": [
      13
    ],
    "75ef29f8": [
      13
    ],
    "75f0fb74": [
      13
    ],
    "17a93b8c": [
      13
    ],
    "177bc670": [
      13
    ],
    "75f8b5c3": [
      13
    ],
    "7602418e": [
      13
    ],
    "374ae6a1": [
      13
    ],
    "382518c1": [
      13
    ],
    "387102ba": [
      13
    ],
    "388e8ed9": [
      13
    ],
    "3891bd72": [
      13
    ],
    "38de9029": [
      13
    ],
    "76039eab": [
      13
    ],
    "40cbcd4f": [
      13
    ],
    "41bd2e5c": [
      13
    ],
    "7605e486": [
      13
    ],
    "760658e5": [
      13
    ],
    "760b58fa": [
      13
    ],
    "760efbf2": [
      13
    ],
    "7611b62c": [
      13
    ],
    "73b24a3a": [
      13
    ],
    "73b578d3": [
      13
    ],
    "761641e2": [
      13
    ],
    "7619707b": [
      13
    ],
    "761acd98": [
      13
    ],
    "761e7090": [
      13
    ],
    "35e78ebe": [
      13
    ],
    "762287e7": [
      13
    ],
    "762b2af4": [
      13
    ],
    "762f424b": [
      13
    ],
    "76309f68": [
      13
    ],
    "94acef9e": [
      13
    ],
    "7636fc9a": [
      13
    ],
    "763dce2b": [
      13
    ],
    "763e428a": [
      13
    ],
    "152575f2": [
      13
    ],
    "7643b6fe": [
      13
    ],
    "764d42c9": [
      13
    ],
    "7651ce7f": [
      13
    ],
    "76565a35": [
      13
    ],
    "765742f3": [
      13
    ],
    "7657b752": [
      13
    ],
    "76582bb1": [
      13
    ],
    "765ae5eb": [
      13
    ],
    "765cb767": [
      13
    ],
    "76605a5f": [
      13
    ],
    "7668890d": [
      13
    ],
    "766971cb": [
      13
    ],
    "766fcefd": [
      13
    ],
    "7671a079": [
      13
    ],
    "7672fd96": [
      13
    ],
    "7673e654": [
      13
    ],
    "7675b7d0": [
      13
    ],
    "76762c2f": [
      13
    ],
    "ff4ed8f4": [
      13
    ],
    "7676a08e": [
      13
    ],
    "7678e669": [
      13
    ],
    "767c8961": [
      13
    ],
    "767de67e": [
      13
    ],
    "754a07a7": [
      13
    ],
    "7681fdd5": [
      13
    ],
    "00e2dd10": [
      13
    ],
    "769d4419": [
      13
    ],
    "76a0e711": [
      13
    ],
    "2777b780": [
      13
    ],
    "76bad038": [
      13
    ],
    "76bd8a72": [
      13
    ],
    "76c3e7a4": [
      13
    ],
    "76c45c03": [
      13
    ],
    "76c62d7f": [
      13
    ],
    "76c7163d": [
      13
    ],
    "76c78a9c": [
      13
    ],
    "76c9d077": [
      13
    ],
    "76ca44d6": [
      13
    ],
    "36943b0a": [
      13
    ],
    "76cab935": [
      13
    ],
    "76cc1652": [
      13
    ],
    "76cc8ab1": [
      13
    ],
    "76d0a208": [
      13
    ],
    "76d27384": [
      13
    ],
    "639aed16": [
      13
    ],
    "76d35c42": [
      13
    ],
    "76d3d0a1": [
      13
    ],
    "355089e8": [
      13
    ],
    "63f81d29": [
      13
    ],
    "76d85c57": [
      13
    ],
    "64bf37b3": [
      13
    ],
    "64bfac12": [
      13
    ],
    "44ac7ee0": [
      13
    ],
    "76e3453f": [
      13
    ],
    "76e673d8": [
      13
    ],
    "76ea16d0": [
      13
    ],
    "22ad1ae2": [
      13
    ],
    "76f07402": [
      13
    ],
    "1d07c0fc": [
      13
    ],
    "771d74bf": [
      13
    ],
    "ff5d3822": [
      13
    ],
    "fed30752": [
      13
    ],
    "fd75ea52": [
      13
    ],
    "9830caf6": [
      15
    ],
    "6254be56": [
      17
    ],
    "4ac5f0ed": [
      17
    ],
    "4c83fb51": [
      15
    ],
    "0e952526": [
      15
    ],
    "7d525186": [
      15
    ],
    "caae263e": [
      15
    ],
    "80acaf88": [
      15
    ],
    "782e264e": [
      15
    ],
    "4375a0b2": [
      15
    ],
    "660bdc36": [
      13
    ],
    "1b135058": [
      13
    ],
    "595ec00f": [
      17
    ],
    "2280bda7": [
      17
    ],
    "5b4350fa": [
      15
    ],
    "6a134ca0": [
      15
    ],
    "6e2c953e": [
      15
    ],
    "217782d2": [
      15
    ],
    "5fbd79be": [
      15
    ],
    "7b91265a": [
      15
    ],
    "ac7d8e1c": [
      15
    ],
    "03500aca": [
      15
    ],
    "c97b1c0a": [
      15
    ],
    "127055ac": [
      15
    ],
    "4d3fcb7b": [
      15
    ],
    "4f8e684f": [
      15
    ],
    "4158021e": [
      15
    ],
    "17be0d72": [
      15
    ],
    "274121bd": [
      15
    ],
    "01a08dce": [
      15
    ],
    "79826eca": [
      15
    ],
    "0267b54d": [
      17
    ],
    "84522bb2": [
      17
    ],
    "163bffbf": [
      17
    ],
    "4deb51be": [
      17
    ],
    "b7e94226": [
      17
    ],
    "28b7709a": [
      17
    ],
    "e38b7aec": [
      17
    ],
    "3cf8c1d6": [
      17
    ],
    "5336c6f4": [
      17
    ],
    "28fa7f80": [
      17
    ],
    "90f94168": [
      17
    ],
    "2384aa72": [
      17
    ],
    "fb2fa376": [
      10
    ],
    "09febdce": [
      10
    ],
    "2dec5e3f": [
      10
    ],
    "37d11f1c": [
      10
    ],
    "60f3d71f": [
      6
    ],
    "919d786c": [
      6
    ],
    "0cd3e555": [
      6
    ],
    "b66e3278": [
      6
    ],
    "5cd8efa3": [
      6
    ],
    "4cd137ae": [
      16
    ],
    "4522a21e": [
      16
    ],
    "69b018b4": [
      16
    ],
    "32ba4518": [
      16
    ],
    "1b2cfdf4": [
      16
    ],
    "613a4ca4": [
      5
    ],
    "6f2aab2f": [
      5
    ],
    "10333f70": [
      5
    ],
    "5cc24e29": [
      5
    ],
    "603849be": [
      5
    ],
    "a67822e4": [
      12
    ],
    "10dfeb0f": [
      12
    ],
    "cb48dcf0": [
      12
    ],
    "60e4f55d": [
      12
    ],
    "4b0e478e": [
      2
    ],
    "3b5b382b": [
      2
    ],
    "94db0074": [
      2
    ],
    "28f2db25": [
      2
    ],
    "05978a14": [
      2
    ],
    "665df47f": [
      9
    ],
    "1239424d": [
      9
    ],
    "53f59779": [
      9
    ],
    "623e4c9b": [
      9
    ],
    "4b1c5f0f": [
      3
    ],
    "0e4ed2b3": [
      3
    ],
    "9381a936": [
      3
    ],
    "083314a6": [
      3
    ],
    "064435b3": [
      3
    ]
  },
  "assetsMapping": {
    "14b5292713a87fca71f8.js": "6b34c3eb",
    "33d9b6ed32073e596aa8.js": "6b34c3ec",
    "3a46c8f4da3860394409.js": "6fca0322",
    "3b9d5998a43562325cfb.js": "6b2ac401",
    "5119cc306d04eb726ae3.js": "6b2ac3fc",
    "56c0a54331558de3e2a5.js": "7ea1d828",
    "86adc34d2adfe7f90fd5.js": "1a3ae26b",
    "8e63b0601df76b940aa3.js": "6b2ac404",
    "8f80bb4528de006b1026.js": "69ae3ae3",
    "8fa100176adb079e28cc.js": "0859c165",
    "908a02b7f09d711d2316.js": "6b2ac402",
    "93f2a62fcd394e319f30.js": "35c7aa70",
    "b02a6835c41741c65550.js": "03a883ea",
    "e21fefb901f3e6c8bfa9.js": "6b34c40b",
    "f1dddc5ee7797b101467.js": "2a130dde"
  }
}